abstract_ai/__init__.py
abstract_ai/abstract_ai_gui.py
abstract_ai/for_react.py
abstract_ai/abstract_QT5/__init__.py
abstract_ai/abstract_QT5/controller.py
abstract_ai/abstract_QT5/pyQt5_ai.py
abstract_ai/abstract_QT5/pyQt5_ai_back.py
abstract_ai/abstract_QT5/urlTry.py
abstract_ai/ai_call_package/__init__.py
abstract_ai/ai_call_package/routes.py
abstract_ai/ai_call_package/apis/__init__.py
abstract_ai/ai_call_package/apis/make_api_calls.py
abstract_ai/ai_call_package/apis/routes.py
abstract_ai/ai_call_package/apis/grok/__init__.py
abstract_ai/ai_call_package/apis/grok/routes.py
abstract_ai/ai_call_package/apis/grok/scripts/__init__.py
abstract_ai/ai_call_package/apis/grok/scripts/general.py
abstract_ai/ai_call_package/apis/grok/scripts/routes.py
abstract_ai/ai_call_package/env_dir/__init__.py
abstract_ai/ai_call_package/env_dir/api_key_retrieval.py
abstract_ai/gpt_classes/__init__.py
abstract_ai/gpt_classes/controller.py
abstract_ai/gpt_classes/api_selection/ApiBuilder.py
abstract_ai/gpt_classes/api_selection/__init__.py
abstract_ai/gpt_classes/file_section/JsonHandler.py
abstract_ai/gpt_classes/file_section/__init__.py
abstract_ai/gpt_classes/file_section/responseContentParser.py
abstract_ai/gpt_classes/gpt_manager/GptManager.py
abstract_ai/gpt_classes/gpt_manager/__init__.py
abstract_ai/gpt_classes/gpt_manager/dependencies.py
abstract_ai/gpt_classes/gpt_manager/get_book.py
abstract_ai/gpt_classes/gpt_manager/instruction_section/__init__.py
abstract_ai/gpt_classes/gpt_manager/instruction_section/instruction_management.py
abstract_ai/gpt_classes/gpt_manager/prompt_section/__init__.py
abstract_ai/gpt_classes/gpt_manager/prompt_section/prompt_management.py
abstract_ai/gpt_classes/gpt_manager/response_section/__init__.py
abstract_ai/gpt_classes/gpt_manager/response_section/output_display.py
abstract_ai/gpt_classes/gpt_manager/response_section/output_file_utils.py
abstract_ai/gpt_classes/gpt_manager/response_section/output_response.py
abstract_ai-0.2.1.159.dist-info/METADATA
abstract_ai-0.2.1.159.dist-info/WHEEL
abstract_ai-0.2.1.159.dist-info/top_level.txt
abstract_ai-0.2.1.159.dist-info/RECORD
