Metadata-Version: 2.4
Name: abstract_ai
Version: 0.2.1.159
Summary: abstract_ai is a Python module that serves as a bridge between your application and the OpenAI GPT-3 API. It provides a convenient interface for sending requests, managing responses, and controlling the behavior of the API calls. This module is highly customizable, allowing you to establish prompts, instructions, and response handling logic.
Home-page: https://github.com/AbstractEndeavors/abstract_ai
Author: putkoff
Author-email: partners@abstractendeavors.com
Classifier: Development Status :: 3 - Alpha
Classifier: Intended Audience :: Developers
Classifier: License :: OSI Approved :: MIT License
Classifier: Programming Language :: Python :: 3
Classifier: Programming Language :: Python :: 3.11
Requires-Python: >=3.6
Requires-Dist: abstract_database
Requires-Dist: abstract_security>=0.0.1
Requires-Dist: abstract_webtools>=0.1.4.90
Requires-Dist: tiktoken>=0.5.1
Requires-Dist: abstract_utilities>=0.2.2.1
Requires-Dist: abstract_gui>=0.0.60.0
Requires-Dist: pyperclip>=1.8.2
Requires-Dist: openai>=0.28.1
Requires-Dist: requests>=2.31.0
Requires-Dist: nltk>=3.8.1
Requires-Dist: python-docx
Dynamic: author
Dynamic: author-email
Dynamic: classifier
Dynamic: description
Dynamic: description-content-type
Dynamic: home-page
Dynamic: requires-dist
Dynamic: requires-python
Dynamic: summary
